<saved-ma-configuration server='OCCCP-AS033' export-date='2012-04-16 00:17:05.152'>
<!--WARNING>
!!!!!!!!!!!!!!!!!!!!!!!!!!!!!!!!!!!!!!!!!!!!!!!!!!!!!!!!!!!!!!!!!!!
!!
!! The contents of this file should not be edited.
!! Any such modifications to this file may result in errors during import.
!!
!!!!!!!!!!!!!!!!!!!!!!!!!!!!!!!!!!!!!!!!!!!!!!!!!!!!!!!!!!!!!!!!!!!
</WARNING-->
<ma-data>
 <format-version>1</format-version>
 <id>{CDF02640-02E3-4F9F-AB7E-CCFE42BD13AA}</id>
 <name>FIM</name>
 <category>FIM</category>
 <subtype/>
 <ma-listname/>
 <ma-companyname/>
 <creation-time>2011-12-23 04:49:23.283</creation-time>
 <last-modification-time>2012-04-15 22:25:55.311</last-modification-time>
 <version>247</version>
 <internal-version>0</internal-version>
 <password-sync-allowed>0</password-sync-allowed>
 <schema>
  <dsml:dsml xmlns:dsml="http://www.dsml.org/DSML" xmlns:ms-dsml="http://www.microsoft.com/MMS/DSML"><dsml:directory-schema ms-dsml:no-objectclass-validation="true"><dsml:class id="DetectedRuleEntry" type="structural"><dsml:name>DetectedRuleEntry</dsml:name><dsml:attribute ref="#ObjectID" required="false" /><dsml:attribute ref="#Connector" required="true" /><dsml:attribute ref="#CreatedTime" required="false" /><dsml:attribute ref="#Creator" required="false" /><dsml:attribute ref="#DeletedTime" required="false" /><dsml:attribute ref="#Description" required="false" /><dsml:attribute ref="#DetectedRulesList" required="false" /><dsml:attribute ref="#DisplayName" required="false" /><dsml:attribute ref="#ExpectedRulesList" required="false" /><dsml:attribute ref="#ExpirationTime" required="false" /><dsml:attribute ref="#Locale" required="false" /><dsml:attribute ref="#MVObjectID" required="false" /><dsml:attribute ref="#ObjectType" required="false" /><dsml:attribute ref="#ResourceParent" required="false" /><dsml:attribute ref="#ResourceTime" required="false" /><dsml:attribute ref="#SynchronizationRuleID" required="false" /></dsml:class><dsml:class id="ExpectedRuleEntry" type="structural"><dsml:name>ExpectedRuleEntry</dsml:name><dsml:attribute ref="#ObjectID" required="false" /><dsml:attribute ref="#CreatedTime" required="false" /><dsml:attribute ref="#Creator" required="false" /><dsml:attribute ref="#DeletedTime" required="false" /><dsml:attribute ref="#Description" required="false" /><dsml:attribute ref="#DetectedRulesList" required="false" /><dsml:attribute ref="#DisplayName" required="false" /><dsml:attribute ref="#ExpectedRuleEntryAction" required="true" /><dsml:attribute ref="#ExpectedRulesList" required="false" /><dsml:attribute ref="#ExpirationTime" required="false" /><dsml:attribute ref="#Locale" required="false" /><dsml:attribute ref="#MVObjectID" required="false" /><dsml:attribute ref="#ObjectType" required="false" /><dsml:attribute ref="#ResourceParent" required="false" /><dsml:attribute ref="#ResourceTime" required="false" /><dsml:attribute ref="#StatusError" required="false" /><dsml:attribute ref="#SynchronizationRuleData" required="false" /><dsml:attribute ref="#SynchronizationRuleID" required="false" /><dsml:attribute ref="#SynchronizationRuleName" required="true" /><dsml:attribute ref="#SynchronizationRuleStatus" required="true" /></dsml:class><dsml:class id="Group" type="structural"><dsml:name>Group</dsml:name><dsml:attribute ref="#ObjectID" required="false" /><dsml:attribute ref="#AccountName" required="false" /><dsml:attribute ref="#CreatedTime" required="false" /><dsml:attribute ref="#Creator" required="false" /><dsml:attribute ref="#DeletedTime" required="false" /><dsml:attribute ref="#Description" required="false" /><dsml:attribute ref="#DetectedRulesList" required="false" /><dsml:attribute ref="#DisplayedOwner" required="false" /><dsml:attribute ref="#DisplayName" required="false" /><dsml:attribute ref="#Domain" required="true" /><dsml:attribute ref="#DomainConfiguration" required="false" /><dsml:attribute ref="#Email" required="false" /><dsml:attribute ref="#ExpectedRulesList" required="false" /><dsml:attribute ref="#ExpirationTime" required="false" /><dsml:attribute ref="#Filter" required="false" /><dsml:attribute ref="#Locale" required="false" /><dsml:attribute ref="#MailNickname" required="false" /><dsml:attribute ref="#MembershipAddWorkflow" required="true" /><dsml:attribute ref="#MembershipLocked" required="true" /><dsml:attribute ref="#MVObjectID" required="false" /><dsml:attribute ref="#ObjectSID" required="false" /><dsml:attribute ref="#ObjectType" required="false" /><dsml:attribute ref="#Owner" required="false" /><dsml:attribute ref="#ResourceTime" required="false" /><dsml:attribute ref="#Scope" required="true" /><dsml:attribute ref="#SIDHistory" required="false" /><dsml:attribute ref="#Temporal" required="false" /><dsml:attribute ref="#Type" required="true" /><dsml:attribute ref="#OU" required="false" /><dsml:attribute ref="#Member" required="false" /></dsml:class><dsml:class id="Person" type="structural"><dsml:name>Person</dsml:name><dsml:attribute ref="#ObjectID" required="false" /><dsml:attribute ref="#AccountName" required="false" /><dsml:attribute ref="#AD_UserCannotChangePassword" required="false" /><dsml:attribute ref="#Address" required="false" /><dsml:attribute ref="#Assistant" required="false" /><dsml:attribute ref="#AuthNLockoutRegistrationID" required="false" /><dsml:attribute ref="#AuthNWFLockedOut" required="false" /><dsml:attribute ref="#AuthNWFRegistered" required="false" /><dsml:attribute ref="#City" required="false" /><dsml:attribute ref="#Company" required="false" /><dsml:attribute ref="#CostCenter" required="false" /><dsml:attribute ref="#CostCenterName" required="false" /><dsml:attribute ref="#Country" required="false" /><dsml:attribute ref="#CreatedTime" required="false" /><dsml:attribute ref="#Creator" required="false" /><dsml:attribute ref="#DeletedTime" required="false" /><dsml:attribute ref="#Department" required="false" /><dsml:attribute ref="#Description" required="false" /><dsml:attribute ref="#DetectedRulesList" required="false" /><dsml:attribute ref="#DisplayName" required="false" /><dsml:attribute ref="#Domain" required="false" /><dsml:attribute ref="#DomainConfiguration" required="false" /><dsml:attribute ref="#Email" required="false" /><dsml:attribute ref="#EmployeeEndDate" required="false" /><dsml:attribute ref="#EmployeeID" required="false" /><dsml:attribute ref="#EmployeeStartDate" required="false" /><dsml:attribute ref="#EmployeeType" required="false" /><dsml:attribute ref="#ExpectedRulesList" required="false" /><dsml:attribute ref="#ExpirationTime" required="false" /><dsml:attribute ref="#FirstName" required="false" /><dsml:attribute ref="#FreezeCount" required="false" /><dsml:attribute ref="#FreezeLevel" required="false" /><dsml:attribute ref="#IsRASEnabled" required="false" /><dsml:attribute ref="#JobTitle" required="false" /><dsml:attribute ref="#LastName" required="false" /><dsml:attribute ref="#LastResetAttemptTime" required="false" /><dsml:attribute ref="#Locale" required="false" /><dsml:attribute ref="#LoginName" required="false" /><dsml:attribute ref="#MailNickname" required="false" /><dsml:attribute ref="#Manager" required="false" /><dsml:attribute ref="#MiddleName" required="false" /><dsml:attribute ref="#MobilePhone" required="false" /><dsml:attribute ref="#MVObjectID" required="false" /><dsml:attribute ref="#ObjectSID" required="false" /><dsml:attribute ref="#ObjectType" required="false" /><dsml:attribute ref="#OfficeFax" required="false" /><dsml:attribute ref="#OfficeLocation" required="false" /><dsml:attribute ref="#OfficePhone" required="false" /><dsml:attribute ref="#Photo" required="false" /><dsml:attribute ref="#PostalCode" required="false" /><dsml:attribute ref="#ProxyAddressCollection" required="false" /><dsml:attribute ref="#Register" required="false" /><dsml:attribute ref="#RegistrationRequired" required="false" /><dsml:attribute ref="#ResetPassword" required="false" /><dsml:attribute ref="#ResourceTime" required="false" /><dsml:attribute ref="#SIDHistory" required="false" /><dsml:attribute ref="#TimeZone" required="false" /><dsml:attribute ref="#Archive" required="false" /><dsml:attribute ref="#Address1" required="false" /><dsml:attribute ref="#AlumniType" required="false" /><dsml:attribute ref="#Address3" required="false" /><dsml:attribute ref="#Address2" required="false" /><dsml:attribute ref="#ADSCODE1" required="false" /><dsml:attribute ref="#AddressID" required="false" /><dsml:attribute ref="#Deceased" required="false" /><dsml:attribute ref="#DateLeft" required="false" /><dsml:attribute ref="#CandidateNumber" required="false" /><dsml:attribute ref="#Class" required="false" /><dsml:attribute ref="#PhoneHome" required="false" /><dsml:attribute ref="#PersonType" required="false" /><dsml:attribute ref="#PhoneMobile" required="false" /><dsml:attribute ref="#NName" required="false" /><dsml:attribute ref="#profilePath" required="false" /><dsml:attribute ref="#PhoneFamily" required="false" /><dsml:attribute ref="#PreEnrolment" required="false" /><dsml:attribute ref="#ReasonLeft" required="false" /><dsml:attribute ref="#Year" required="false" /><dsml:attribute ref="#USIN" required="false" /><dsml:attribute ref="#test" required="false" /><dsml:attribute ref="#StudentType" required="false" /><dsml:attribute ref="#StartYear" required="false" /><dsml:attribute ref="#SAS2IDMConnector" required="false" /><dsml:attribute ref="#SchoolCode" required="false" /><dsml:attribute ref="#Sex" required="false" /><dsml:attribute ref="#StartDate" required="false" /><dsml:attribute ref="#SchoolID" required="false" /><dsml:attribute ref="#EmployeeNumber" required="false" /><dsml:attribute ref="#DOB" required="false" /><dsml:attribute ref="#Mailsuffix" required="false" /><dsml:attribute ref="#FormerName" required="false" /><dsml:attribute ref="#HomeGroup" required="false" /><dsml:attribute ref="#House" required="false" /><dsml:attribute ref="#PreferredName" required="false" /></dsml:class><dsml:class id="SynchronizationRule" type="structural"><dsml:name>SynchronizationRule</dsml:name><dsml:attribute ref="#ObjectID" required="false" /><dsml:attribute ref="#ConnectedObjectType" required="true" /><dsml:attribute ref="#ConnectedSystem" required="true" /><dsml:attribute ref="#ConnectedSystemScope" required="false" /><dsml:attribute ref="#CreateConnectedSystemObject" required="true" /><dsml:attribute ref="#CreatedTime" required="false" /><dsml:attribute ref="#CreateILMObject" required="true" /><dsml:attribute ref="#Creator" required="false" /><dsml:attribute ref="#DeletedTime" required="false" /><dsml:attribute ref="#Dependency" required="false" /><dsml:attribute ref="#Description" required="false" /><dsml:attribute ref="#DetectedRulesList" required="false" /><dsml:attribute ref="#DisconnectConnectedSystemObject" required="true" /><dsml:attribute ref="#DisplayName" required="false" /><dsml:attribute ref="#ExistenceTest" required="false" /><dsml:attribute ref="#ExpectedRulesList" required="false" /><dsml:attribute ref="#ExpirationTime" required="false" /><dsml:attribute ref="#FlowType" required="true" /><dsml:attribute ref="#ILMObjectType" required="true" /><dsml:attribute ref="#InitialFlow" required="false" /><dsml:attribute ref="#Locale" required="false" /><dsml:attribute ref="#MVObjectID" required="false" /><dsml:attribute ref="#ObjectType" required="false" /><dsml:attribute ref="#PersistentFlow" required="false" /><dsml:attribute ref="#Precedence" required="false" /><dsml:attribute ref="#RelationshipCriteria" required="true" /><dsml:attribute ref="#ResourceTime" required="false" /><dsml:attribute ref="#SynchronizationRuleParameters" required="false" /><dsml:attribute ref="#ManagementAgentID" required="false" /></dsml:class><dsml:attribute-type id="ObjectID" single-value="true" isreadonly="true" ms-dsml:immutable="true"><dsml:name>ObjectID</dsml:name><dsml:syntax>1.3.6.1.4.1.1466.115.121.1.12</dsml:syntax></dsml:attribute-type><dsml:attribute-type id="Connector" single-value="true"><dsml:name>Connector</dsml:name><dsml:syntax>1.3.6.1.4.1.1466.115.121.1.15</dsml:syntax></dsml:attribute-type><dsml:attribute-type id="CreatedTime" single-value="true" isreadonly="true"><dsml:name>CreatedTime</dsml:name><dsml:syntax>1.3.6.1.4.1.1466.115.121.1.15</dsml:syntax></dsml:attribute-type><dsml:attribute-type id="Creator" single-value="true" isreadonly="true"><dsml:name>Creator</dsml:name><dsml:syntax>1.3.6.1.4.1.1466.115.121.1.12</dsml:syntax></dsml:attribute-type><dsml:attribute-type id="DeletedTime" single-value="true" isreadonly="true"><dsml:name>DeletedTime</dsml:name><dsml:syntax>1.3.6.1.4.1.1466.115.121.1.15</dsml:syntax></dsml:attribute-type><dsml:attribute-type id="Description" single-value="true"><dsml:name>Description</dsml:name><dsml:syntax>1.3.6.1.4.1.1466.115.121.1.15</dsml:syntax></dsml:attribute-type><dsml:attribute-type id="DetectedRulesList" single-value="false"><dsml:name>DetectedRulesList</dsml:name><dsml:syntax>1.3.6.1.4.1.1466.115.121.1.12</dsml:syntax></dsml:attribute-type><dsml:attribute-type id="DisplayName" single-value="true"><dsml:name>DisplayName</dsml:name><dsml:syntax>1.3.6.1.4.1.1466.115.121.1.15</dsml:syntax></dsml:attribute-type><dsml:attribute-type id="ExpectedRulesList" single-value="false"><dsml:name>ExpectedRulesList</dsml:name><dsml:syntax>1.3.6.1.4.1.1466.115.121.1.12</dsml:syntax></dsml:attribute-type><dsml:attribute-type id="ExpirationTime" single-value="true"><dsml:name>ExpirationTime</dsml:name><dsml:syntax>1.3.6.1.4.1.1466.115.121.1.15</dsml:syntax></dsml:attribute-type><dsml:attribute-type id="Locale" single-value="true" isreadonly="true"><dsml:name>Locale</dsml:name><dsml:syntax>1.3.6.1.4.1.1466.115.121.1.15</dsml:syntax></dsml:attribute-type><dsml:attribute-type id="MVObjectID" single-value="true"><dsml:name>MVObjectID</dsml:name><dsml:syntax>1.3.6.1.4.1.1466.115.121.1.15</dsml:syntax></dsml:attribute-type><dsml:attribute-type id="ObjectType" single-value="true" isreadonly="true"><dsml:name>ObjectType</dsml:name><dsml:syntax>1.3.6.1.4.1.1466.115.121.1.15</dsml:syntax></dsml:attribute-type><dsml:attribute-type id="ResourceParent" single-value="true"><dsml:name>ResourceParent</dsml:name><dsml:syntax>1.3.6.1.4.1.1466.115.121.1.12</dsml:syntax></dsml:attribute-type><dsml:attribute-type id="ResourceTime" single-value="true" isreadonly="true"><dsml:name>ResourceTime</dsml:name><dsml:syntax>1.3.6.1.4.1.1466.115.121.1.15</dsml:syntax></dsml:attribute-type><dsml:attribute-type id="SynchronizationRuleID" single-value="true"><dsml:name>SynchronizationRuleID</dsml:name><dsml:syntax>1.3.6.1.4.1.1466.115.121.1.12</dsml:syntax></dsml:attribute-type><dsml:attribute-type id="ExpectedRuleEntryAction" single-value="true"><dsml:name>ExpectedRuleEntryAction</dsml:name><dsml:syntax>1.3.6.1.4.1.1466.115.121.1.15</dsml:syntax></dsml:attribute-type><dsml:attribute-type id="StatusError" single-value="true"><dsml:name>StatusError</dsml:name><dsml:syntax>1.3.6.1.4.1.1466.115.121.1.15</dsml:syntax></dsml:attribute-type><dsml:attribute-type id="SynchronizationRuleData" single-value="false"><dsml:name>SynchronizationRuleData</dsml:name><dsml:syntax>1.3.6.1.4.1.1466.115.121.1.15</dsml:syntax></dsml:attribute-type><dsml:attribute-type id="SynchronizationRuleName" single-value="true"><dsml:name>SynchronizationRuleName</dsml:name><dsml:syntax>1.3.6.1.4.1.1466.115.121.1.15</dsml:syntax></dsml:attribute-type><dsml:attribute-type id="SynchronizationRuleStatus" single-value="true"><dsml:name>SynchronizationRuleStatus</dsml:name><dsml:syntax>1.3.6.1.4.1.1466.115.121.1.15</dsml:syntax></dsml:attribute-type><dsml:attribute-type id="AccountName" single-value="true"><dsml:name>AccountName</dsml:name><dsml:syntax>1.3.6.1.4.1.1466.115.121.1.15</dsml:syntax></dsml:attribute-type><dsml:attribute-type id="DisplayedOwner" single-value="true"><dsml:name>DisplayedOwner</dsml:name><dsml:syntax>1.3.6.1.4.1.1466.115.121.1.12</dsml:syntax></dsml:attribute-type><dsml:attribute-type id="Domain" single-value="true"><dsml:name>Domain</dsml:name><dsml:syntax>1.3.6.1.4.1.1466.115.121.1.15</dsml:syntax></dsml:attribute-type><dsml:attribute-type id="DomainConfiguration" single-value="true"><dsml:name>DomainConfiguration</dsml:name><dsml:syntax>1.3.6.1.4.1.1466.115.121.1.12</dsml:syntax></dsml:attribute-type><dsml:attribute-type id="Email" single-value="true"><dsml:name>Email</dsml:name><dsml:syntax>1.3.6.1.4.1.1466.115.121.1.15</dsml:syntax></dsml:attribute-type><dsml:attribute-type id="Filter" single-value="true"><dsml:name>Filter</dsml:name><dsml:syntax>1.3.6.1.4.1.1466.115.121.1.15</dsml:syntax></dsml:attribute-type><dsml:attribute-type id="MailNickname" single-value="true"><dsml:name>MailNickname</dsml:name><dsml:syntax>1.3.6.1.4.1.1466.115.121.1.15</dsml:syntax></dsml:attribute-type><dsml:attribute-type id="MembershipAddWorkflow" single-value="true"><dsml:name>MembershipAddWorkflow</dsml:name><dsml:syntax>1.3.6.1.4.1.1466.115.121.1.15</dsml:syntax></dsml:attribute-type><dsml:attribute-type id="MembershipLocked" single-value="true"><dsml:name>MembershipLocked</dsml:name><dsml:syntax>1.3.6.1.4.1.1466.115.121.1.7</dsml:syntax></dsml:attribute-type><dsml:attribute-type id="ObjectSID" single-value="true"><dsml:name>ObjectSID</dsml:name><dsml:syntax>1.3.6.1.4.1.1466.115.121.1.5</dsml:syntax></dsml:attribute-type><dsml:attribute-type id="Owner" single-value="false"><dsml:name>Owner</dsml:name><dsml:syntax>1.3.6.1.4.1.1466.115.121.1.12</dsml:syntax></dsml:attribute-type><dsml:attribute-type id="Scope" single-value="true"><dsml:name>Scope</dsml:name><dsml:syntax>1.3.6.1.4.1.1466.115.121.1.15</dsml:syntax></dsml:attribute-type><dsml:attribute-type id="SIDHistory" single-value="false"><dsml:name>SIDHistory</dsml:name><dsml:syntax>1.3.6.1.4.1.1466.115.121.1.5</dsml:syntax></dsml:attribute-type><dsml:attribute-type id="Temporal" single-value="true"><dsml:name>Temporal</dsml:name><dsml:syntax>1.3.6.1.4.1.1466.115.121.1.7</dsml:syntax></dsml:attribute-type><dsml:attribute-type id="Type" single-value="true"><dsml:name>Type</dsml:name><dsml:syntax>1.3.6.1.4.1.1466.115.121.1.15</dsml:syntax></dsml:attribute-type><dsml:attribute-type id="OU" single-value="true"><dsml:name>OU</dsml:name><dsml:syntax>1.3.6.1.4.1.1466.115.121.1.15</dsml:syntax></dsml:attribute-type><dsml:attribute-type id="Member" single-value="false"><dsml:name>Member</dsml:name><dsml:syntax>1.3.6.1.4.1.1466.115.121.1.12</dsml:syntax></dsml:attribute-type><dsml:attribute-type id="AD_UserCannotChangePassword" single-value="true"><dsml:name>AD_UserCannotChangePassword</dsml:name><dsml:syntax>1.3.6.1.4.1.1466.115.121.1.7</dsml:syntax></dsml:attribute-type><dsml:attribute-type id="Address" single-value="true"><dsml:name>Address</dsml:name><dsml:syntax>1.3.6.1.4.1.1466.115.121.1.15</dsml:syntax></dsml:attribute-type><dsml:attribute-type id="Assistant" single-value="true"><dsml:name>Assistant</dsml:name><dsml:syntax>1.3.6.1.4.1.1466.115.121.1.12</dsml:syntax></dsml:attribute-type><dsml:attribute-type id="AuthNLockoutRegistrationID" single-value="false"><dsml:name>AuthNLockoutRegistrationID</dsml:name><dsml:syntax>1.3.6.1.4.1.1466.115.121.1.12</dsml:syntax></dsml:attribute-type><dsml:attribute-type id="AuthNWFLockedOut" single-value="false"><dsml:name>AuthNWFLockedOut</dsml:name><dsml:syntax>1.3.6.1.4.1.1466.115.121.1.12</dsml:syntax></dsml:attribute-type><dsml:attribute-type id="AuthNWFRegistered" single-value="false"><dsml:name>AuthNWFRegistered</dsml:name><dsml:syntax>1.3.6.1.4.1.1466.115.121.1.12</dsml:syntax></dsml:attribute-type><dsml:attribute-type id="City" single-value="true"><dsml:name>City</dsml:name><dsml:syntax>1.3.6.1.4.1.1466.115.121.1.15</dsml:syntax></dsml:attribute-type><dsml:attribute-type id="Company" single-value="true"><dsml:name>Company</dsml:name><dsml:syntax>1.3.6.1.4.1.1466.115.121.1.15</dsml:syntax></dsml:attribute-type><dsml:attribute-type id="CostCenter" single-value="true"><dsml:name>CostCenter</dsml:name><dsml:syntax>1.3.6.1.4.1.1466.115.121.1.15</dsml:syntax></dsml:attribute-type><dsml:attribute-type id="CostCenterName" single-value="true"><dsml:name>CostCenterName</dsml:name><dsml:syntax>1.3.6.1.4.1.1466.115.121.1.15</dsml:syntax></dsml:attribute-type><dsml:attribute-type id="Country" single-value="true"><dsml:name>Country</dsml:name><dsml:syntax>1.3.6.1.4.1.1466.115.121.1.15</dsml:syntax></dsml:attribute-type><dsml:attribute-type id="Department" single-value="true"><dsml:name>Department</dsml:name><dsml:syntax>1.3.6.1.4.1.1466.115.121.1.15</dsml:syntax></dsml:attribute-type><dsml:attribute-type id="EmployeeEndDate" single-value="true"><dsml:name>EmployeeEndDate</dsml:name><dsml:syntax>1.3.6.1.4.1.1466.115.121.1.15</dsml:syntax></dsml:attribute-type><dsml:attribute-type id="EmployeeID" single-value="true"><dsml:name>EmployeeID</dsml:name><dsml:syntax>1.3.6.1.4.1.1466.115.121.1.15</dsml:syntax></dsml:attribute-type><dsml:attribute-type id="EmployeeStartDate" single-value="true"><dsml:name>EmployeeStartDate</dsml:name><dsml:syntax>1.3.6.1.4.1.1466.115.121.1.15</dsml:syntax></dsml:attribute-type><dsml:attribute-type id="EmployeeType" single-value="true"><dsml:name>EmployeeType</dsml:name><dsml:syntax>1.3.6.1.4.1.1466.115.121.1.15</dsml:syntax></dsml:attribute-type><dsml:attribute-type id="FirstName" single-value="true"><dsml:name>FirstName</dsml:name><dsml:syntax>1.3.6.1.4.1.1466.115.121.1.15</dsml:syntax></dsml:attribute-type><dsml:attribute-type id="FreezeCount" single-value="true"><dsml:name>FreezeCount</dsml:name><dsml:syntax>1.3.6.1.4.1.1466.115.121.1.27</dsml:syntax></dsml:attribute-type><dsml:attribute-type id="FreezeLevel" single-value="true"><dsml:name>FreezeLevel</dsml:name><dsml:syntax>1.3.6.1.4.1.1466.115.121.1.15</dsml:syntax></dsml:attribute-type><dsml:attribute-type id="IsRASEnabled" single-value="true"><dsml:name>IsRASEnabled</dsml:name><dsml:syntax>1.3.6.1.4.1.1466.115.121.1.7</dsml:syntax></dsml:attribute-type><dsml:attribute-type id="JobTitle" single-value="true"><dsml:name>JobTitle</dsml:name><dsml:syntax>1.3.6.1.4.1.1466.115.121.1.15</dsml:syntax></dsml:attribute-type><dsml:attribute-type id="LastName" single-value="true"><dsml:name>LastName</dsml:name><dsml:syntax>1.3.6.1.4.1.1466.115.121.1.15</dsml:syntax></dsml:attribute-type><dsml:attribute-type id="LastResetAttemptTime" single-value="true"><dsml:name>LastResetAttemptTime</dsml:name><dsml:syntax>1.3.6.1.4.1.1466.115.121.1.15</dsml:syntax></dsml:attribute-type><dsml:attribute-type id="LoginName" single-value="true"><dsml:name>LoginName</dsml:name><dsml:syntax>1.3.6.1.4.1.1466.115.121.1.15</dsml:syntax></dsml:attribute-type><dsml:attribute-type id="Manager" single-value="true"><dsml:name>Manager</dsml:name><dsml:syntax>1.3.6.1.4.1.1466.115.121.1.12</dsml:syntax></dsml:attribute-type><dsml:attribute-type id="MiddleName" single-value="true"><dsml:name>MiddleName</dsml:name><dsml:syntax>1.3.6.1.4.1.1466.115.121.1.15</dsml:syntax></dsml:attribute-type><dsml:attribute-type id="MobilePhone" single-value="true"><dsml:name>MobilePhone</dsml:name><dsml:syntax>1.3.6.1.4.1.1466.115.121.1.15</dsml:syntax></dsml:attribute-type><dsml:attribute-type id="OfficeFax" single-value="true"><dsml:name>OfficeFax</dsml:name><dsml:syntax>1.3.6.1.4.1.1466.115.121.1.15</dsml:syntax></dsml:attribute-type><dsml:attribute-type id="OfficeLocation" single-value="true"><dsml:name>OfficeLocation</dsml:name><dsml:syntax>1.3.6.1.4.1.1466.115.121.1.15</dsml:syntax></dsml:attribute-type><dsml:attribute-type id="OfficePhone" single-value="true"><dsml:name>OfficePhone</dsml:name><dsml:syntax>1.3.6.1.4.1.1466.115.121.1.15</dsml:syntax></dsml:attribute-type><dsml:attribute-type id="Photo" single-value="true"><dsml:name>Photo</dsml:name><dsml:syntax>1.3.6.1.4.1.1466.115.121.1.5</dsml:syntax></dsml:attribute-type><dsml:attribute-type id="PostalCode" single-value="true"><dsml:name>PostalCode</dsml:name><dsml:syntax>1.3.6.1.4.1.1466.115.121.1.15</dsml:syntax></dsml:attribute-type><dsml:attribute-type id="ProxyAddressCollection" single-value="false"><dsml:name>ProxyAddressCollection</dsml:name><dsml:syntax>1.3.6.1.4.1.1466.115.121.1.15</dsml:syntax></dsml:attribute-type><dsml:attribute-type id="Register" single-value="true"><dsml:name>Register</dsml:name><dsml:syntax>1.3.6.1.4.1.1466.115.121.1.7</dsml:syntax></dsml:attribute-type><dsml:attribute-type id="RegistrationRequired" single-value="true"><dsml:name>RegistrationRequired</dsml:name><dsml:syntax>1.3.6.1.4.1.1466.115.121.1.7</dsml:syntax></dsml:attribute-type><dsml:attribute-type id="ResetPassword" single-value="true"><dsml:name>ResetPassword</dsml:name><dsml:syntax>1.3.6.1.4.1.1466.115.121.1.15</dsml:syntax></dsml:attribute-type><dsml:attribute-type id="TimeZone" single-value="true"><dsml:name>TimeZone</dsml:name><dsml:syntax>1.3.6.1.4.1.1466.115.121.1.12</dsml:syntax></dsml:attribute-type><dsml:attribute-type id="Archive" single-value="true"><dsml:name>Archive</dsml:name><dsml:syntax>1.3.6.1.4.1.1466.115.121.1.15</dsml:syntax></dsml:attribute-type><dsml:attribute-type id="Address1" single-value="true"><dsml:name>Address1</dsml:name><dsml:syntax>1.3.6.1.4.1.1466.115.121.1.15</dsml:syntax></dsml:attribute-type><dsml:attribute-type id="AlumniType" single-value="true"><dsml:name>AlumniType</dsml:name><dsml:syntax>1.3.6.1.4.1.1466.115.121.1.15</dsml:syntax></dsml:attribute-type><dsml:attribute-type id="Address3" single-value="true"><dsml:name>Address3</dsml:name><dsml:syntax>1.3.6.1.4.1.1466.115.121.1.15</dsml:syntax></dsml:attribute-type><dsml:attribute-type id="Address2" single-value="true"><dsml:name>Address2</dsml:name><dsml:syntax>1.3.6.1.4.1.1466.115.121.1.15</dsml:syntax></dsml:attribute-type><dsml:attribute-type id="ADSCODE1" single-value="true"><dsml:name>ADSCODE1</dsml:name><dsml:syntax>1.3.6.1.4.1.1466.115.121.1.15</dsml:syntax></dsml:attribute-type><dsml:attribute-type id="AddressID" single-value="true"><dsml:name>AddressID</dsml:name><dsml:syntax>1.3.6.1.4.1.1466.115.121.1.27</dsml:syntax></dsml:attribute-type><dsml:attribute-type id="Deceased" single-value="true"><dsml:name>Deceased</dsml:name><dsml:syntax>1.3.6.1.4.1.1466.115.121.1.15</dsml:syntax></dsml:attribute-type><dsml:attribute-type id="DateLeft" single-value="true"><dsml:name>DateLeft</dsml:name><dsml:syntax>1.3.6.1.4.1.1466.115.121.1.15</dsml:syntax></dsml:attribute-type><dsml:attribute-type id="CandidateNumber" single-value="true"><dsml:name>CandidateNumber</dsml:name><dsml:syntax>1.3.6.1.4.1.1466.115.121.1.15</dsml:syntax></dsml:attribute-type><dsml:attribute-type id="Class" single-value="true"><dsml:name>Class</dsml:name><dsml:syntax>1.3.6.1.4.1.1466.115.121.1.15</dsml:syntax></dsml:attribute-type><dsml:attribute-type id="PhoneHome" single-value="true"><dsml:name>PhoneHome</dsml:name><dsml:syntax>1.3.6.1.4.1.1466.115.121.1.15</dsml:syntax></dsml:attribute-type><dsml:attribute-type id="PersonType" single-value="true"><dsml:name>PersonType</dsml:name><dsml:syntax>1.3.6.1.4.1.1466.115.121.1.15</dsml:syntax></dsml:attribute-type><dsml:attribute-type id="PhoneMobile" single-value="true"><dsml:name>PhoneMobile</dsml:name><dsml:syntax>1.3.6.1.4.1.1466.115.121.1.15</dsml:syntax></dsml:attribute-type><dsml:attribute-type id="NName" single-value="true"><dsml:name>NName</dsml:name><dsml:syntax>1.3.6.1.4.1.1466.115.121.1.15</dsml:syntax></dsml:attribute-type><dsml:attribute-type id="profilePath" single-value="true"><dsml:name>profilePath</dsml:name><dsml:syntax>1.3.6.1.4.1.1466.115.121.1.15</dsml:syntax></dsml:attribute-type><dsml:attribute-type id="PhoneFamily" single-value="true"><dsml:name>PhoneFamily</dsml:name><dsml:syntax>1.3.6.1.4.1.1466.115.121.1.15</dsml:syntax></dsml:attribute-type><dsml:attribute-type id="PreEnrolment" single-value="true"><dsml:name>PreEnrolment</dsml:name><dsml:syntax>1.3.6.1.4.1.1466.115.121.1.15</dsml:syntax></dsml:attribute-type><dsml:attribute-type id="ReasonLeft" single-value="true"><dsml:name>ReasonLeft</dsml:name><dsml:syntax>1.3.6.1.4.1.1466.115.121.1.15</dsml:syntax></dsml:attribute-type><dsml:attribute-type id="Year" single-value="true"><dsml:name>Year</dsml:name><dsml:syntax>1.3.6.1.4.1.1466.115.121.1.15</dsml:syntax></dsml:attribute-type><dsml:attribute-type id="USIN" single-value="true"><dsml:name>USIN</dsml:name><dsml:syntax>1.3.6.1.4.1.1466.115.121.1.15</dsml:syntax></dsml:attribute-type><dsml:attribute-type id="test" single-value="true"><dsml:name>test</dsml:name><dsml:syntax>1.3.6.1.4.1.1466.115.121.1.15</dsml:syntax></dsml:attribute-type><dsml:attribute-type id="StudentType" single-value="true"><dsml:name>StudentType</dsml:name><dsml:syntax>1.3.6.1.4.1.1466.115.121.1.15</dsml:syntax></dsml:attribute-type><dsml:attribute-type id="StartYear" single-value="true"><dsml:name>StartYear</dsml:name><dsml:syntax>1.3.6.1.4.1.1466.115.121.1.15</dsml:syntax></dsml:attribute-type><dsml:attribute-type id="SAS2IDMConnector" single-value="true"><dsml:name>SAS2IDMConnector</dsml:name><dsml:syntax>1.3.6.1.4.1.1466.115.121.1.7</dsml:syntax></dsml:attribute-type><dsml:attribute-type id="SchoolCode" single-value="true"><dsml:name>SchoolCode</dsml:name><dsml:syntax>1.3.6.1.4.1.1466.115.121.1.15</dsml:syntax></dsml:attribute-type><dsml:attribute-type id="Sex" single-value="true"><dsml:name>Sex</dsml:name><dsml:syntax>1.3.6.1.4.1.1466.115.121.1.15</dsml:syntax></dsml:attribute-type><dsml:attribute-type id="StartDate" single-value="true"><dsml:name>StartDate</dsml:name><dsml:syntax>1.3.6.1.4.1.1466.115.121.1.15</dsml:syntax></dsml:attribute-type><dsml:attribute-type id="SchoolID" single-value="true"><dsml:name>SchoolID</dsml:name><dsml:syntax>1.3.6.1.4.1.1466.115.121.1.27</dsml:syntax></dsml:attribute-type><dsml:attribute-type id="EmployeeNumber" single-value="true"><dsml:name>EmployeeNumber</dsml:name><dsml:syntax>1.3.6.1.4.1.1466.115.121.1.15</dsml:syntax></dsml:attribute-type><dsml:attribute-type id="DOB" single-value="true"><dsml:name>DOB</dsml:name><dsml:syntax>1.3.6.1.4.1.1466.115.121.1.15</dsml:syntax></dsml:attribute-type><dsml:attribute-type id="Mailsuffix" single-value="true"><dsml:name>Mailsuffix</dsml:name><dsml:syntax>1.3.6.1.4.1.1466.115.121.1.15</dsml:syntax></dsml:attribute-type><dsml:attribute-type id="FormerName" single-value="true"><dsml:name>FormerName</dsml:name><dsml:syntax>1.3.6.1.4.1.1466.115.121.1.15</dsml:syntax></dsml:attribute-type><dsml:attribute-type id="HomeGroup" single-value="true"><dsml:name>HomeGroup</dsml:name><dsml:syntax>1.3.6.1.4.1.1466.115.121.1.15</dsml:syntax></dsml:attribute-type><dsml:attribute-type id="House" single-value="true"><dsml:name>House</dsml:name><dsml:syntax>1.3.6.1.4.1.1466.115.121.1.15</dsml:syntax></dsml:attribute-type><dsml:attribute-type id="PreferredName" single-value="true"><dsml:name>PreferredName</dsml:name><dsml:syntax>1.3.6.1.4.1.1466.115.121.1.15</dsml:syntax></dsml:attribute-type><dsml:attribute-type id="ConnectedObjectType" single-value="true"><dsml:name>ConnectedObjectType</dsml:name><dsml:syntax>1.3.6.1.4.1.1466.115.121.1.15</dsml:syntax></dsml:attribute-type><dsml:attribute-type id="ConnectedSystem" single-value="true"><dsml:name>ConnectedSystem</dsml:name><dsml:syntax>1.3.6.1.4.1.1466.115.121.1.15</dsml:syntax></dsml:attribute-type><dsml:attribute-type id="ConnectedSystemScope" single-value="true"><dsml:name>ConnectedSystemScope</dsml:name><dsml:syntax>1.3.6.1.4.1.1466.115.121.1.15</dsml:syntax></dsml:attribute-type><dsml:attribute-type id="CreateConnectedSystemObject" single-value="true"><dsml:name>CreateConnectedSystemObject</dsml:name><dsml:syntax>1.3.6.1.4.1.1466.115.121.1.7</dsml:syntax></dsml:attribute-type><dsml:attribute-type id="CreateILMObject" single-value="true"><dsml:name>CreateILMObject</dsml:name><dsml:syntax>1.3.6.1.4.1.1466.115.121.1.7</dsml:syntax></dsml:attribute-type><dsml:attribute-type id="Dependency" single-value="true"><dsml:name>Dependency</dsml:name><dsml:syntax>1.3.6.1.4.1.1466.115.121.1.12</dsml:syntax></dsml:attribute-type><dsml:attribute-type id="DisconnectConnectedSystemObject" single-value="true"><dsml:name>DisconnectConnectedSystemObject</dsml:name><dsml:syntax>1.3.6.1.4.1.1466.115.121.1.7</dsml:syntax></dsml:attribute-type><dsml:attribute-type id="ExistenceTest" single-value="false"><dsml:name>ExistenceTest</dsml:name><dsml:syntax>1.3.6.1.4.1.1466.115.121.1.15</dsml:syntax></dsml:attribute-type><dsml:attribute-type id="FlowType" single-value="true"><dsml:name>FlowType</dsml:name><dsml:syntax>1.3.6.1.4.1.1466.115.121.1.27</dsml:syntax></dsml:attribute-type><dsml:attribute-type id="ILMObjectType" single-value="true"><dsml:name>ILMObjectType</dsml:name><dsml:syntax>1.3.6.1.4.1.1466.115.121.1.15</dsml:syntax></dsml:attribute-type><dsml:attribute-type id="InitialFlow" single-value="false"><dsml:name>InitialFlow</dsml:name><dsml:syntax>1.3.6.1.4.1.1466.115.121.1.15</dsml:syntax></dsml:attribute-type><dsml:attribute-type id="PersistentFlow" single-value="false"><dsml:name>PersistentFlow</dsml:name><dsml:syntax>1.3.6.1.4.1.1466.115.121.1.15</dsml:syntax></dsml:attribute-type><dsml:attribute-type id="Precedence" single-value="true"><dsml:name>Precedence</dsml:name><dsml:syntax>1.3.6.1.4.1.1466.115.121.1.27</dsml:syntax></dsml:attribute-type><dsml:attribute-type id="RelationshipCriteria" single-value="true"><dsml:name>RelationshipCriteria</dsml:name><dsml:syntax>1.3.6.1.4.1.1466.115.121.1.15</dsml:syntax></dsml:attribute-type><dsml:attribute-type id="SynchronizationRuleParameters" single-value="false"><dsml:name>SynchronizationRuleParameters</dsml:name><dsml:syntax>1.3.6.1.4.1.1466.115.121.1.15</dsml:syntax></dsml:attribute-type><dsml:attribute-type id="ManagementAgentID" single-value="true"><dsml:name>ManagementAgentID</dsml:name><dsml:syntax>1.3.6.1.4.1.1466.115.121.1.12</dsml:syntax></dsml:attribute-type></dsml:directory-schema></dsml:dsml>
 </schema>
 <attribute-inclusion><attribute>AccountName</attribute><attribute>AD_UserCannotChangePassword</attribute><attribute>Address</attribute><attribute>Address1</attribute><attribute>Address2</attribute><attribute>Address3</attribute><attribute>AddressID</attribute><attribute>AlumniType</attribute><attribute>Archive</attribute><attribute>Assistant</attribute><attribute>AuthNLockoutRegistrationID</attribute><attribute>AuthNWFLockedOut</attribute><attribute>AuthNWFRegistered</attribute><attribute>CandidateNumber</attribute><attribute>City</attribute><attribute>Class</attribute><attribute>Company</attribute><attribute>ConnectedObjectType</attribute><attribute>ConnectedSystem</attribute><attribute>ConnectedSystemScope</attribute><attribute>Connector</attribute><attribute>CostCenter</attribute><attribute>CostCenterName</attribute><attribute>Country</attribute><attribute>CreateConnectedSystemObject</attribute><attribute>CreatedTime</attribute><attribute>CreateILMObject</attribute><attribute>Creator</attribute><attribute>DateLeft</attribute><attribute>Deceased</attribute><attribute>DeletedTime</attribute><attribute>Department</attribute><attribute>Dependency</attribute><attribute>Description</attribute><attribute>DetectedRulesList</attribute><attribute>DisconnectConnectedSystemObject</attribute><attribute>DisplayName</attribute><attribute>DOB</attribute><attribute>Domain</attribute><attribute>DomainConfiguration</attribute><attribute>Email</attribute><attribute>EmployeeEndDate</attribute><attribute>EmployeeID</attribute><attribute>EmployeeNumber</attribute><attribute>EmployeeStartDate</attribute><attribute>EmployeeType</attribute><attribute>ExistenceTest</attribute><attribute>ExpectedRuleEntryAction</attribute><attribute>ExpectedRulesList</attribute><attribute>ExpirationTime</attribute><attribute>Filter</attribute><attribute>FirstName</attribute><attribute>FlowType</attribute><attribute>FormerName</attribute><attribute>FreezeCount</attribute><attribute>FreezeLevel</attribute><attribute>HomeGroup</attribute><attribute>House</attribute><attribute>ILMObjectType</attribute><attribute>InitialFlow</attribute><attribute>IsRASEnabled</attribute><attribute>JobTitle</attribute><attribute>LastName</attribute><attribute>LastResetAttemptTime</attribute><attribute>Locale</attribute><attribute>LoginName</attribute><attribute>MailNickname</attribute><attribute>Mailsuffix</attribute><attribute>ManagementAgentID</attribute><attribute>Manager</attribute><attribute>Member</attribute><attribute>MembershipAddWorkflow</attribute><attribute>MembershipLocked</attribute><attribute>MiddleName</attribute><attribute>MobilePhone</attribute><attribute>MVObjectID</attribute><attribute>NName</attribute><attribute>ObjectID</attribute><attribute>ObjectSID</attribute><attribute>ObjectType</attribute><attribute>OfficeFax</attribute><attribute>OfficeLocation</attribute><attribute>OfficePhone</attribute><attribute>OU</attribute><attribute>Owner</attribute><attribute>PersistentFlow</attribute><attribute>PersonType</attribute><attribute>PhoneFamily</attribute><attribute>PhoneHome</attribute><attribute>PhoneMobile</attribute><attribute>Photo</attribute><attribute>PostalCode</attribute><attribute>Precedence</attribute><attribute>PreEnrolment</attribute><attribute>PreferredName</attribute><attribute>ProxyAddressCollection</attribute><attribute>ReasonLeft</attribute><attribute>Register</attribute><attribute>RegistrationRequired</attribute><attribute>RelationshipCriteria</attribute><attribute>ResetPassword</attribute><attribute>ResourceParent</attribute><attribute>ResourceTime</attribute><attribute>SAS2IDMConnector</attribute><attribute>SchoolCode</attribute><attribute>SchoolID</attribute><attribute>Scope</attribute><attribute>Sex</attribute><attribute>SIDHistory</attribute><attribute>StartDate</attribute><attribute>StartYear</attribute><attribute>StatusError</attribute><attribute>StudentType</attribute><attribute>SynchronizationRuleData</attribute><attribute>SynchronizationRuleID</attribute><attribute>SynchronizationRuleName</attribute><attribute>SynchronizationRuleParameters</attribute><attribute>SynchronizationRuleStatus</attribute><attribute>TimeZone</attribute><attribute>Type</attribute><attribute>USIN</attribute><attribute>Year</attribute></attribute-inclusion>
 <stay-disconnector><filter-set cd-object-type="Person" type="declared"><filter-alternative id="{16B0B380-3D68-4731-8935-E6DB0A7EE65F}"><condition cd-attribute="DisplayName" operator="equality"><value>FIM_PortalAdmin</value></condition></filter-alternative><filter-alternative id="{59F8E975-14C5-449D-BA25-247B7B2A7676}"><condition cd-attribute="DisplayName" operator="equality"><value>Built-in Synchronization Account</value></condition></filter-alternative></filter-set></stay-disconnector>
 <join><join-profile cd-object-type="DetectedRuleEntry"><join-criterion id="{FB02F9C0-B87C-46CE-97F6-E47E0316884F}"><search mv-object-type="detectedRuleEntry"><attribute-mapping mv-attribute="csObjectID"><direct-mapping><src-attribute intrinsic="true">dn</src-attribute></direct-mapping></attribute-mapping></search><resolution type="none"><script-context></script-context></resolution></join-criterion><join-criterion id="{6DE9653C-62C1-4DAF-8743-4AE433A306C4}"><search mv-object-type="detectedRuleEntry"><attribute-mapping mv-attribute="object-id" intrinsic-attribute="true"><direct-mapping><src-attribute>MVObjectID</src-attribute></direct-mapping></attribute-mapping></search><resolution type="none"><script-context></script-context></resolution></join-criterion></join-profile><join-profile cd-object-type="ExpectedRuleEntry"><join-criterion id="{6B60CC68-CA58-42FC-B122-B1B261DBC871}"><search mv-object-type="expectedRuleEntry"><attribute-mapping mv-attribute="csObjectID"><direct-mapping><src-attribute intrinsic="true">dn</src-attribute></direct-mapping></attribute-mapping></search><resolution type="none"><script-context></script-context></resolution></join-criterion><join-criterion id="{0D81B89B-286E-4F72-90F7-939DD611A9C3}"><search mv-object-type="expectedRuleEntry"><attribute-mapping mv-attribute="object-id" intrinsic-attribute="true"><direct-mapping><src-attribute>MVObjectID</src-attribute></direct-mapping></attribute-mapping></search><resolution type="none"><script-context></script-context></resolution></join-criterion></join-profile><join-profile cd-object-type="Group"><join-criterion id="{ABC1674C-704A-41E8-9E2F-EF2A0CC4B6C7}"><search mv-object-type="group"><attribute-mapping mv-attribute="csObjectID"><direct-mapping><src-attribute intrinsic="true">dn</src-attribute></direct-mapping></attribute-mapping></search><resolution type="none"><script-context></script-context></resolution></join-criterion><join-criterion id="{843CFFA5-B420-4BDB-B62D-E6A2B31C6F7A}"><search mv-object-type="group"><attribute-mapping mv-attribute="object-id" intrinsic-attribute="true"><direct-mapping><src-attribute>MVObjectID</src-attribute></direct-mapping></attribute-mapping></search><resolution type="none"><script-context></script-context></resolution></join-criterion></join-profile><join-profile cd-object-type="Person"><join-criterion id="{6244D304-0D3D-4843-8490-1303668078B1}"><search mv-object-type="person"><attribute-mapping mv-attribute="csObjectID"><direct-mapping><src-attribute intrinsic="true">dn</src-attribute></direct-mapping></attribute-mapping></search><resolution type="none"><script-context></script-context></resolution></join-criterion><join-criterion id="{5E1428DF-0FAA-4187-9780-D1711809324D}"><search mv-object-type="person"><attribute-mapping mv-attribute="object-id" intrinsic-attribute="true"><direct-mapping><src-attribute>MVObjectID</src-attribute></direct-mapping></attribute-mapping></search><resolution type="none"><script-context></script-context></resolution></join-criterion></join-profile><join-profile cd-object-type="SynchronizationRule"><join-criterion id="{F9FD7305-C556-426C-8928-97F6276F80FB}"><search mv-object-type="synchronizationRule"><attribute-mapping mv-attribute="csObjectID"><direct-mapping><src-attribute intrinsic="true">dn</src-attribute></direct-mapping></attribute-mapping></search><resolution type="none"><script-context></script-context></resolution></join-criterion><join-criterion id="{7F382187-11E1-4281-9109-8BF68CA10FA2}"><search mv-object-type="synchronizationRule"><attribute-mapping mv-attribute="object-id" intrinsic-attribute="true"><direct-mapping><src-attribute>MVObjectID</src-attribute></direct-mapping></attribute-mapping></search><resolution type="none"><script-context></script-context></resolution></join-criterion></join-profile></join>
 <projection><class-mapping type="declared" id="{0D63FA4E-56E7-44FC-BC74-8C827E131468}" cd-object-type="DetectedRuleEntry"><mv-object-type>detectedRuleEntry</mv-object-type></class-mapping><class-mapping type="declared" id="{5E9AF71F-9C9D-44D8-8A04-6C66B319F635}" cd-object-type="ExpectedRuleEntry"><mv-object-type>expectedRuleEntry</mv-object-type></class-mapping><class-mapping type="declared" id="{5B670717-B764-42BD-A2CF-9C58F51DFD7E}" cd-object-type="Group"><mv-object-type>group</mv-object-type></class-mapping><class-mapping type="declared" id="{849C2EEF-874C-4885-9A47-00ECEE4272D5}" cd-object-type="Person"><mv-object-type>person</mv-object-type></class-mapping><class-mapping type="declared" id="{D856524B-2821-4135-B653-16988418B645}" cd-object-type="SynchronizationRule"><mv-object-type>synchronizationRule</mv-object-type></class-mapping></projection>
 <export-attribute-flow><export-flow-set cd-object-type="DetectedRuleEntry" mv-object-type="detectedRuleEntry"><export-flow cd-attribute="SynchronizationRuleID" id="{F2F8143F-9477-40B8-B2C6-3064D916B54A}" suppress-deletions="true"><direct-mapping><src-attribute>synchronizationRuleID</src-attribute></direct-mapping></export-flow><export-flow cd-attribute="DisplayName" id="{990D134B-0B36-4391-9A68-8C9D2F5894A7}" suppress-deletions="true"><direct-mapping><src-attribute>displayName</src-attribute></direct-mapping></export-flow><export-flow cd-attribute="Connector" id="{A7BABB09-5199-4858-9CA9-F3A3CDF95DEF}" suppress-deletions="true"><direct-mapping><src-attribute>connector</src-attribute></direct-mapping></export-flow><export-flow cd-attribute="ResourceParent" id="{C9CF3C15-A8D1-4781-A066-AE11A0280B5C}" suppress-deletions="true"><direct-mapping><src-attribute>resourceParent</src-attribute></direct-mapping></export-flow><export-flow cd-attribute="dn" id="{0C94C8F9-BAAC-425E-AB4E-4E67452A60B9}"><sync-rule-mapping mapping-type="expression" sync-rule-id="{22953763-AB04-473D-903D-4CE791620B43}" sync-rule-mapping-id="{22953763-AB04-473D-903D-4CE791620B43}" initial-flow-only="true"><sync-rule-value><export-flow><dest>dn</dest><src><attr /></src><fn id="Guid" /></export-flow></sync-rule-value></sync-rule-mapping></export-flow><export-flow cd-attribute="MVObjectID" id="{13EE066F-5ECF-42B4-A3EB-19E03EFECDFE}" suppress-deletions="true"><direct-mapping><src-attribute intrinsic="true">object-id</src-attribute></direct-mapping></export-flow></export-flow-set><export-flow-set cd-object-type="ExpectedRuleEntry" mv-object-type="expectedRuleEntry"><export-flow cd-attribute="StatusError" id="{C10BE2D8-5E7C-459A-838C-5BDF134DFCA8}" suppress-deletions="true"><direct-mapping><src-attribute>statusError</src-attribute></direct-mapping></export-flow><export-flow cd-attribute="SynchronizationRuleStatus" id="{46A15AE4-DA0E-4BD8-9426-5392D3C8975D}" suppress-deletions="true"><direct-mapping><src-attribute>status</src-attribute></direct-mapping></export-flow></export-flow-set><export-flow-set cd-object-type="Person" mv-object-type="person"><export-flow cd-attribute="dn" id="{53B59654-EE88-484A-956B-8D9AC20DB05B}"><sync-rule-mapping mapping-type="expression" sync-rule-id="{6A1FBD8A-1FD4-4BC7-B16E-22BD0DEA7CBC}" sync-rule-mapping-id="{6A1FBD8A-1FD4-4BC7-B16E-22BD0DEA7CBC}" initial-flow-only="true"><sync-rule-value><export-flow><dest>dn</dest><src><attr /></src><fn id="Guid" /></export-flow></sync-rule-value></sync-rule-mapping></export-flow><export-flow cd-attribute="MVObjectID" id="{C60AF63E-6554-41A2-A87A-50AC2A7F9971}" suppress-deletions="true"><direct-mapping><src-attribute intrinsic="true">object-id</src-attribute></direct-mapping></export-flow><export-flow cd-attribute="DetectedRulesList" id="{A84E21F2-F4D3-40A4-BE9A-A604948557C3}" suppress-deletions="false"><direct-mapping><src-attribute>detectedRulesList</src-attribute></direct-mapping></export-flow><export-flow cd-attribute="FirstName" id="{4FA09103-C921-4D29-B140-02E1FA926208}" suppress-deletions="false"><direct-mapping><src-attribute>givenName</src-attribute></direct-mapping></export-flow><export-flow cd-attribute="DOB" id="{A2317236-ECE7-4221-973E-0446CEF862D0}" suppress-deletions="false"><direct-mapping><src-attribute>DOB</src-attribute></direct-mapping></export-flow><export-flow cd-attribute="MiddleName" id="{530EA9B3-3135-466D-A6FB-B1B3733FFCEF}" suppress-deletions="false"><direct-mapping><src-attribute>middleName</src-attribute></direct-mapping></export-flow><export-flow cd-attribute="LastName" id="{2BD60649-53D6-4FE2-A315-2268787D47E4}" suppress-deletions="false"><direct-mapping><src-attribute>lastName</src-attribute></direct-mapping></export-flow><export-flow cd-attribute="PreferredName" id="{4741748D-D523-43EB-AE6C-965A61483718}" suppress-deletions="false"><direct-mapping><src-attribute>PreferredName</src-attribute></direct-mapping></export-flow><export-flow cd-attribute="NName" id="{B5D9782E-9065-483A-82B5-031B5A5167A9}" suppress-deletions="false"><direct-mapping><src-attribute>NName</src-attribute></direct-mapping></export-flow><export-flow cd-attribute="FormerName" id="{35620810-C2D1-477C-8015-EF5E3FF2F89D}" suppress-deletions="false"><direct-mapping><src-attribute>FormerName</src-attribute></direct-mapping></export-flow><export-flow cd-attribute="Sex" id="{B76F37BA-5020-47B7-BF8C-2654C16007DB}" suppress-deletions="false"><direct-mapping><src-attribute>Sex</src-attribute></direct-mapping></export-flow><export-flow cd-attribute="Year" id="{51ED0819-4A56-403F-9E5A-A882141ABAD9}" suppress-deletions="false"><direct-mapping><src-attribute>Year</src-attribute></direct-mapping></export-flow><export-flow cd-attribute="Class" id="{E2D6630E-076E-41B1-B544-46DCF1D4783D}" suppress-deletions="false"><direct-mapping><src-attribute>Class</src-attribute></direct-mapping></export-flow><export-flow cd-attribute="HomeGroup" id="{EDAD0D44-A0A1-4D21-A825-59A862E8DA1F}" suppress-deletions="false"><direct-mapping><src-attribute>HomeGroup</src-attribute></direct-mapping></export-flow><export-flow cd-attribute="House" id="{839251A7-97D0-4252-A2E2-468E5A4618F4}" suppress-deletions="false"><direct-mapping><src-attribute>House</src-attribute></direct-mapping></export-flow><export-flow cd-attribute="AddressID" id="{9B42D5B5-3C6D-43F7-A6B3-62FDB14475FE}" suppress-deletions="false"><direct-mapping><src-attribute>AddressID</src-attribute></direct-mapping></export-flow><export-flow cd-attribute="Address1" id="{368E0C9E-5609-4CFC-84E4-1BC662475A7F}" suppress-deletions="false"><direct-mapping><src-attribute>Address1</src-attribute></direct-mapping></export-flow><export-flow cd-attribute="Address2" id="{764980F5-E09B-4631-8F01-0C58BA181BA3}" suppress-deletions="false"><direct-mapping><src-attribute>Address2</src-attribute></direct-mapping></export-flow><export-flow cd-attribute="Address3" id="{8D64AD92-0BAC-4869-AAF7-4C7F665E0D73}" suppress-deletions="false"><direct-mapping><src-attribute>Address3</src-attribute></direct-mapping></export-flow><export-flow cd-attribute="PostalCode" id="{9640A91D-B290-4D2A-BCA4-6B2C060748AB}" suppress-deletions="false"><direct-mapping><src-attribute>postalCode</src-attribute></direct-mapping></export-flow><export-flow cd-attribute="Country" id="{62B8AAD0-7B71-490C-AA11-A09158C8FFE0}" suppress-deletions="false"><direct-mapping><src-attribute>country</src-attribute></direct-mapping></export-flow><export-flow cd-attribute="Email" id="{BCB55A4F-EA66-4728-B70C-D1837007F816}" suppress-deletions="false"><direct-mapping><src-attribute>mail</src-attribute></direct-mapping></export-flow><export-flow cd-attribute="PhoneFamily" id="{50907DF5-5F22-47A0-A1DC-DD774147E3F7}" suppress-deletions="false"><direct-mapping><src-attribute>PhoneFamily</src-attribute></direct-mapping></export-flow><export-flow cd-attribute="PhoneHome" id="{1DF9C992-AF43-4B47-833E-4B864C66D391}" suppress-deletions="false"><direct-mapping><src-attribute>PhoneHome</src-attribute></direct-mapping></export-flow><export-flow cd-attribute="PhoneMobile" id="{BA6B387E-6FA8-4F63-8F88-D200D536CB1A}" suppress-deletions="false"><direct-mapping><src-attribute>PhoneMobile</src-attribute></direct-mapping></export-flow><export-flow cd-attribute="StartYear" id="{A78A7DD0-05D9-4220-947D-DB6E0080672E}" suppress-deletions="false"><direct-mapping><src-attribute>StartYear</src-attribute></direct-mapping></export-flow><export-flow cd-attribute="StartDate" id="{BE75A942-8855-4536-82E0-36879D5B41A3}" suppress-deletions="false"><direct-mapping><src-attribute>StartDate</src-attribute></direct-mapping></export-flow><export-flow cd-attribute="Deceased" id="{68A5ED00-D512-4C38-98DC-EFCEC3BC159F}" suppress-deletions="false"><direct-mapping><src-attribute>Deceased</src-attribute></direct-mapping></export-flow><export-flow cd-attribute="ReasonLeft" id="{FAD76F75-6974-4393-BF15-63BD2E5BD205}" suppress-deletions="false"><direct-mapping><src-attribute>ReasonLeft</src-attribute></direct-mapping></export-flow><export-flow cd-attribute="CandidateNumber" id="{3746E24E-6CF8-4C9D-8DAE-269396564D43}" suppress-deletions="false"><direct-mapping><src-attribute>CandidateNumber</src-attribute></direct-mapping></export-flow><export-flow cd-attribute="USIN" id="{188DA76B-BB11-49A1-917E-3FB913659216}" suppress-deletions="false"><direct-mapping><src-attribute>USIN</src-attribute></direct-mapping></export-flow><export-flow cd-attribute="AlumniType" id="{9BA3CAA0-0637-45F5-BB7D-5B325B35D3CD}" suppress-deletions="false"><direct-mapping><src-attribute>AlumniType</src-attribute></direct-mapping></export-flow><export-flow cd-attribute="PreEnrolment" id="{FDED77A3-4255-4A33-859C-40A1F92789A7}" suppress-deletions="false"><direct-mapping><src-attribute>PreEnrolment</src-attribute></direct-mapping></export-flow><export-flow cd-attribute="Archive" id="{5093D2ED-C26E-4DB6-8E34-896D372EE91B}" suppress-deletions="false"><direct-mapping><src-attribute>Archive</src-attribute></direct-mapping></export-flow><export-flow cd-attribute="PersonType" id="{E7A62EE1-B8E5-41EC-8794-B61893B0D631}" suppress-deletions="false"><direct-mapping><src-attribute>PersonType</src-attribute></direct-mapping></export-flow><export-flow cd-attribute="SAS2IDMConnector" id="{B69649ED-CEF3-432B-A819-2BAB12842BCF}" suppress-deletions="false"><direct-mapping><src-attribute>SAS2IDMConnector</src-attribute></direct-mapping></export-flow><export-flow cd-attribute="Mailsuffix" id="{053285DE-8831-4D8C-99B7-6A28F472D57A}" suppress-deletions="false"><direct-mapping><src-attribute>MailSuffix</src-attribute></direct-mapping></export-flow><export-flow cd-attribute="OfficeLocation" id="{DFF7035B-8DFF-4084-B350-9B89C797172E}" suppress-deletions="true"><direct-mapping><src-attribute>physicalDeliveryOfficeName</src-attribute></direct-mapping></export-flow><export-flow cd-attribute="Description" id="{7FC6F3FA-3D50-45D9-8133-2DA0C0499FAB}" suppress-deletions="true"><direct-mapping><src-attribute>description</src-attribute></direct-mapping></export-flow><export-flow cd-attribute="DisplayName" id="{39AD278A-CC59-4258-BA8C-5BA2DE7558B8}" suppress-deletions="true"><direct-mapping><src-attribute>displayName</src-attribute></direct-mapping></export-flow><export-flow cd-attribute="EmployeeNumber" id="{BD96885C-F2F5-4CCB-86D9-1D62F0F4094B}" suppress-deletions="true"><direct-mapping><src-attribute>EmployeeNumber</src-attribute></direct-mapping></export-flow><export-flow cd-attribute="AccountName" id="{7209E7F4-E3E0-46E9-9D89-CE3E29BE66B2}" suppress-deletions="true"><direct-mapping><src-attribute>accountName</src-attribute></direct-mapping></export-flow></export-flow-set><export-flow-set cd-object-type="Group" mv-object-type="group"><export-flow cd-attribute="dn" id="{AAB162E7-3064-4C8B-A349-2317D4A643D3}"><sync-rule-mapping mapping-type="expression" sync-rule-id="{D471B58B-AFE5-4E27-829F-B15121DB02F0}" sync-rule-mapping-id="{D471B58B-AFE5-4E27-829F-B15121DB02F0}" initial-flow-only="true"><sync-rule-value><export-flow><dest>dn</dest><src><attr /></src><fn id="Guid" /></export-flow></sync-rule-value></sync-rule-mapping></export-flow><export-flow cd-attribute="MVObjectID" id="{2A6A6F10-607F-45FC-9AEA-AA889BE42677}" suppress-deletions="true"><direct-mapping><src-attribute intrinsic="true">object-id</src-attribute></direct-mapping></export-flow><export-flow cd-attribute="DetectedRulesList" id="{6491995D-58F3-422F-AF99-34068E901A08}" suppress-deletions="false"><direct-mapping><src-attribute>detectedRulesList</src-attribute></direct-mapping></export-flow></export-flow-set></export-attribute-flow>
 <provisioning-cleanup type="declared"><action>delete-object</action></provisioning-cleanup>
 <extension />
 <controller-configuration>
 <application-protection>low</application-protection>
 <application-architecture>process</application-architecture>
</controller-configuration>

 <description></description>
 <ma-ui-settings><account-joiner-queries><attributes><cs><attribute name="EmployeeID" header="EmployeeID" size="100" /><attribute name="EmployeeNumber" header="EmployeeNumber" size="100" /><attribute name="DisplayName" header="DisplayName" size="155" /></cs><mv /></attributes><filters max_mv_search_results="" /></account-joiner-queries></ma-ui-settings>
 <private-configuration>
  <fimma-configuration><mms-info><column-info name="DetectedRuleEntry"><column><name>ObjectID</name><data-type>Reference</data-type><isrequired>0</isrequired><ismultivalued>0</ismultivalued></column><column><name>Connector</name><data-type>String</data-type><isrequired>1</isrequired><ismultivalued>0</ismultivalued></column><column><name>CreatedTime</name><data-type>DateTime</data-type><isrequired>1</isrequired><ismultivalued>0</ismultivalued></column><column><name>Creator</name><data-type>Reference</data-type><isrequired>0</isrequired><ismultivalued>0</ismultivalued></column><column><name>DeletedTime</name><data-type>DateTime</data-type><isrequired>0</isrequired><ismultivalued>0</ismultivalued></column><column><name>Description</name><data-type>String</data-type><isrequired>0</isrequired><ismultivalued>0</ismultivalued></column><column><name>DetectedRulesList</name><data-type>Reference</data-type><isrequired>0</isrequired><ismultivalued>1</ismultivalued></column><column><name>DisplayName</name><data-type>String</data-type><isrequired>0</isrequired><ismultivalued>0</ismultivalued></column><column><name>ExpectedRulesList</name><data-type>Reference</data-type><isrequired>0</isrequired><ismultivalued>1</ismultivalued></column><column><name>ExpirationTime</name><data-type>DateTime</data-type><isrequired>0</isrequired><ismultivalued>0</ismultivalued></column><column><name>Locale</name><data-type>String</data-type><isrequired>0</isrequired><ismultivalued>0</ismultivalued></column><column><name>MVObjectID</name><data-type>String</data-type><isrequired>0</isrequired><ismultivalued>0</ismultivalued></column><column><name>ObjectType</name><data-type>String</data-type><isrequired>1</isrequired><ismultivalued>0</ismultivalued></column><column><name>ResourceParent</name><data-type>Reference</data-type><isrequired>0</isrequired><ismultivalued>0</ismultivalued></column><column><name>ResourceTime</name><data-type>DateTime</data-type><isrequired>0</isrequired><ismultivalued>0</ismultivalued></column><column><name>SynchronizationRuleID</name><data-type>Reference</data-type><isrequired>0</isrequired><ismultivalued>0</ismultivalued></column></column-info><column-info name="ExpectedRuleEntry"><column><name>ObjectID</name><data-type>Reference</data-type><isrequired>0</isrequired><ismultivalued>0</ismultivalued></column><column><name>CreatedTime</name><data-type>DateTime</data-type><isrequired>1</isrequired><ismultivalued>0</ismultivalued></column><column><name>Creator</name><data-type>Reference</data-type><isrequired>0</isrequired><ismultivalued>0</ismultivalued></column><column><name>DeletedTime</name><data-type>DateTime</data-type><isrequired>0</isrequired><ismultivalued>0</ismultivalued></column><column><name>Description</name><data-type>String</data-type><isrequired>0</isrequired><ismultivalued>0</ismultivalued></column><column><name>DetectedRulesList</name><data-type>Reference</data-type><isrequired>0</isrequired><ismultivalued>1</ismultivalued></column><column><name>DisplayName</name><data-type>String</data-type><isrequired>0</isrequired><ismultivalued>0</ismultivalued></column><column><name>ExpectedRuleEntryAction</name><data-type>String</data-type><isrequired>1</isrequired><ismultivalued>0</ismultivalued></column><column><name>ExpectedRulesList</name><data-type>Reference</data-type><isrequired>0</isrequired><ismultivalued>1</ismultivalued></column><column><name>ExpirationTime</name><data-type>DateTime</data-type><isrequired>0</isrequired><ismultivalued>0</ismultivalued></column><column><name>Locale</name><data-type>String</data-type><isrequired>0</isrequired><ismultivalued>0</ismultivalued></column><column><name>MVObjectID</name><data-type>String</data-type><isrequired>0</isrequired><ismultivalued>0</ismultivalued></column><column><name>ObjectType</name><data-type>String</data-type><isrequired>1</isrequired><ismultivalued>0</ismultivalued></column><column><name>ResourceParent</name><data-type>Reference</data-type><isrequired>0</isrequired><ismultivalued>0</ismultivalued></column><column><name>ResourceTime</name><data-type>DateTime</data-type><isrequired>0</isrequired><ismultivalued>0</ismultivalued></column><column><name>StatusError</name><data-type>String</data-type><isrequired>0</isrequired><ismultivalued>0</ismultivalued></column><column><name>SynchronizationRuleData</name><data-type>String</data-type><isrequired>0</isrequired><ismultivalued>1</ismultivalued></column><column><name>SynchronizationRuleID</name><data-type>Reference</data-type><isrequired>0</isrequired><ismultivalued>0</ismultivalued></column><column><name>SynchronizationRuleName</name><data-type>String</data-type><isrequired>1</isrequired><ismultivalued>0</ismultivalued></column><column><name>SynchronizationRuleStatus</name><data-type>String</data-type><isrequired>1</isrequired><ismultivalued>0</ismultivalued></column></column-info><column-info name="Group" isDynamic="1"><column><name>ObjectID</name><data-type>Reference</data-type><isrequired>0</isrequired><ismultivalued>0</ismultivalued></column><column><name>AccountName</name><data-type>String</data-type><isrequired>0</isrequired><ismultivalued>0</ismultivalued></column><column><name>CreatedTime</name><data-type>DateTime</data-type><isrequired>1</isrequired><ismultivalued>0</ismultivalued></column><column><name>Creator</name><data-type>Reference</data-type><isrequired>0</isrequired><ismultivalued>0</ismultivalued></column><column><name>DeletedTime</name><data-type>DateTime</data-type><isrequired>0</isrequired><ismultivalued>0</ismultivalued></column><column><name>Description</name><data-type>String</data-type><isrequired>0</isrequired><ismultivalued>0</ismultivalued></column><column><name>DetectedRulesList</name><data-type>Reference</data-type><isrequired>0</isrequired><ismultivalued>1</ismultivalued></column><column><name>DisplayedOwner</name><data-type>Reference</data-type><isrequired>0</isrequired><ismultivalued>0</ismultivalued></column><column><name>DisplayName</name><data-type>String</data-type><isrequired>0</isrequired><ismultivalued>0</ismultivalued></column><column><name>Domain</name><data-type>String</data-type><isrequired>1</isrequired><ismultivalued>0</ismultivalued></column><column><name>DomainConfiguration</name><data-type>Reference</data-type><isrequired>0</isrequired><ismultivalued>0</ismultivalued></column><column><name>Email</name><data-type>String</data-type><isrequired>0</isrequired><ismultivalued>0</ismultivalued></column><column><name>ExpectedRulesList</name><data-type>Reference</data-type><isrequired>0</isrequired><ismultivalued>1</ismultivalued></column><column><name>ExpirationTime</name><data-type>DateTime</data-type><isrequired>0</isrequired><ismultivalued>0</ismultivalued></column><column><name>Filter</name><data-type>Text</data-type><isrequired>0</isrequired><ismultivalued>0</ismultivalued></column><column><name>Locale</name><data-type>String</data-type><isrequired>0</isrequired><ismultivalued>0</ismultivalued></column><column><name>MailNickname</name><data-type>String</data-type><isrequired>0</isrequired><ismultivalued>0</ismultivalued></column><column><name>MembershipAddWorkflow</name><data-type>String</data-type><isrequired>1</isrequired><ismultivalued>0</ismultivalued></column><column><name>MembershipLocked</name><data-type>Boolean</data-type><isrequired>1</isrequired><ismultivalued>0</ismultivalued></column><column><name>MVObjectID</name><data-type>String</data-type><isrequired>0</isrequired><ismultivalued>0</ismultivalued></column><column><name>ObjectSID</name><data-type>Binary</data-type><isrequired>0</isrequired><ismultivalued>0</ismultivalued></column><column><name>ObjectType</name><data-type>String</data-type><isrequired>1</isrequired><ismultivalued>0</ismultivalued></column><column><name>Owner</name><data-type>Reference</data-type><isrequired>0</isrequired><ismultivalued>1</ismultivalued></column><column><name>ResourceTime</name><data-type>DateTime</data-type><isrequired>0</isrequired><ismultivalued>0</ismultivalued></column><column><name>Scope</name><data-type>String</data-type><isrequired>1</isrequired><ismultivalued>0</ismultivalued></column><column><name>SIDHistory</name><data-type>Binary</data-type><isrequired>0</isrequired><ismultivalued>1</ismultivalued></column><column><name>Temporal</name><data-type>Boolean</data-type><isrequired>0</isrequired><ismultivalued>0</ismultivalued></column><column><name>Type</name><data-type>String</data-type><isrequired>1</isrequired><ismultivalued>0</ismultivalued></column><column><name>OU</name><data-type>String</data-type><isrequired>0</isrequired><ismultivalued>0</ismultivalued></column><column><name>Member</name><data-type>Reference</data-type><isrequired>0</isrequired><ismultivalued>1</ismultivalued></column></column-info><column-info name="Person"><column><name>ObjectID</name><data-type>Reference</data-type><isrequired>0</isrequired><ismultivalued>0</ismultivalued></column><column><name>AccountName</name><data-type>String</data-type><isrequired>0</isrequired><ismultivalued>0</ismultivalued></column><column><name>AD_UserCannotChangePassword</name><data-type>Boolean</data-type><isrequired>0</isrequired><ismultivalued>0</ismultivalued></column><column><name>Address</name><data-type>String</data-type><isrequired>0</isrequired><ismultivalued>0</ismultivalued></column><column><name>Assistant</name><data-type>Reference</data-type><isrequired>0</isrequired><ismultivalued>0</ismultivalued></column><column><name>AuthNLockoutRegistrationID</name><data-type>Reference</data-type><isrequired>0</isrequired><ismultivalued>1</ismultivalued></column><column><name>AuthNWFLockedOut</name><data-type>Reference</data-type><isrequired>0</isrequired><ismultivalued>1</ismultivalued></column><column><name>AuthNWFRegistered</name><data-type>Reference</data-type><isrequired>0</isrequired><ismultivalued>1</ismultivalued></column><column><name>City</name><data-type>String</data-type><isrequired>0</isrequired><ismultivalued>0</ismultivalued></column><column><name>Company</name><data-type>String</data-type><isrequired>0</isrequired><ismultivalued>0</ismultivalued></column><column><name>CostCenter</name><data-type>String</data-type><isrequired>0</isrequired><ismultivalued>0</ismultivalued></column><column><name>CostCenterName</name><data-type>String</data-type><isrequired>0</isrequired><ismultivalued>0</ismultivalued></column><column><name>Country</name><data-type>String</data-type><isrequired>0</isrequired><ismultivalued>0</ismultivalued></column><column><name>CreatedTime</name><data-type>DateTime</data-type><isrequired>1</isrequired><ismultivalued>0</ismultivalued></column><column><name>Creator</name><data-type>Reference</data-type><isrequired>0</isrequired><ismultivalued>0</ismultivalued></column><column><name>DeletedTime</name><data-type>DateTime</data-type><isrequired>0</isrequired><ismultivalued>0</ismultivalued></column><column><name>Department</name><data-type>String</data-type><isrequired>0</isrequired><ismultivalued>0</ismultivalued></column><column><name>Description</name><data-type>String</data-type><isrequired>0</isrequired><ismultivalued>0</ismultivalued></column><column><name>DetectedRulesList</name><data-type>Reference</data-type><isrequired>0</isrequired><ismultivalued>1</ismultivalued></column><column><name>DisplayName</name><data-type>String</data-type><isrequired>0</isrequired><ismultivalued>0</ismultivalued></column><column><name>Domain</name><data-type>String</data-type><isrequired>0</isrequired><ismultivalued>0</ismultivalued></column><column><name>DomainConfiguration</name><data-type>Reference</data-type><isrequired>0</isrequired><ismultivalued>0</ismultivalued></column><column><name>Email</name><data-type>String</data-type><isrequired>0</isrequired><ismultivalued>0</ismultivalued></column><column><name>EmployeeEndDate</name><data-type>DateTime</data-type><isrequired>0</isrequired><ismultivalued>0</ismultivalued></column><column><name>EmployeeID</name><data-type>String</data-type><isrequired>0</isrequired><ismultivalued>0</ismultivalued></column><column><name>EmployeeStartDate</name><data-type>DateTime</data-type><isrequired>0</isrequired><ismultivalued>0</ismultivalued></column><column><name>EmployeeType</name><data-type>String</data-type><isrequired>0</isrequired><ismultivalued>0</ismultivalued></column><column><name>ExpectedRulesList</name><data-type>Reference</data-type><isrequired>0</isrequired><ismultivalued>1</ismultivalued></column><column><name>ExpirationTime</name><data-type>DateTime</data-type><isrequired>0</isrequired><ismultivalued>0</ismultivalued></column><column><name>FirstName</name><data-type>String</data-type><isrequired>0</isrequired><ismultivalued>0</ismultivalued></column><column><name>FreezeCount</name><data-type>Integer</data-type><isrequired>0</isrequired><ismultivalued>0</ismultivalued></column><column><name>FreezeLevel</name><data-type>String</data-type><isrequired>0</isrequired><ismultivalued>0</ismultivalued></column><column><name>IsRASEnabled</name><data-type>Boolean</data-type><isrequired>0</isrequired><ismultivalued>0</ismultivalued></column><column><name>JobTitle</name><data-type>String</data-type><isrequired>0</isrequired><ismultivalued>0</ismultivalued></column><column><name>LastName</name><data-type>String</data-type><isrequired>0</isrequired><ismultivalued>0</ismultivalued></column><column><name>LastResetAttemptTime</name><data-type>DateTime</data-type><isrequired>0</isrequired><ismultivalued>0</ismultivalued></column><column><name>Locale</name><data-type>String</data-type><isrequired>0</isrequired><ismultivalued>0</ismultivalued></column><column><name>LoginName</name><data-type>String</data-type><isrequired>0</isrequired><ismultivalued>0</ismultivalued></column><column><name>MailNickname</name><data-type>String</data-type><isrequired>0</isrequired><ismultivalued>0</ismultivalued></column><column><name>Manager</name><data-type>Reference</data-type><isrequired>0</isrequired><ismultivalued>0</ismultivalued></column><column><name>MiddleName</name><data-type>String</data-type><isrequired>0</isrequired><ismultivalued>0</ismultivalued></column><column><name>MobilePhone</name><data-type>String</data-type><isrequired>0</isrequired><ismultivalued>0</ismultivalued></column><column><name>MVObjectID</name><data-type>String</data-type><isrequired>0</isrequired><ismultivalued>0</ismultivalued></column><column><name>ObjectSID</name><data-type>Binary</data-type><isrequired>0</isrequired><ismultivalued>0</ismultivalued></column><column><name>ObjectType</name><data-type>String</data-type><isrequired>1</isrequired><ismultivalued>0</ismultivalued></column><column><name>OfficeFax</name><data-type>String</data-type><isrequired>0</isrequired><ismultivalued>0</ismultivalued></column><column><name>OfficeLocation</name><data-type>String</data-type><isrequired>0</isrequired><ismultivalued>0</ismultivalued></column><column><name>OfficePhone</name><data-type>String</data-type><isrequired>0</isrequired><ismultivalued>0</ismultivalued></column><column><name>Photo</name><data-type>Binary</data-type><isrequired>0</isrequired><ismultivalued>0</ismultivalued></column><column><name>PostalCode</name><data-type>String</data-type><isrequired>0</isrequired><ismultivalued>0</ismultivalued></column><column><name>ProxyAddressCollection</name><data-type>String</data-type><isrequired>0</isrequired><ismultivalued>1</ismultivalued></column><column><name>Register</name><data-type>Boolean</data-type><isrequired>0</isrequired><ismultivalued>0</ismultivalued></column><column><name>RegistrationRequired</name><data-type>Boolean</data-type><isrequired>0</isrequired><ismultivalued>0</ismultivalued></column><column><name>ResetPassword</name><data-type>String</data-type><isrequired>0</isrequired><ismultivalued>0</ismultivalued></column><column><name>ResourceTime</name><data-type>DateTime</data-type><isrequired>0</isrequired><ismultivalued>0</ismultivalued></column><column><name>SIDHistory</name><data-type>Binary</data-type><isrequired>0</isrequired><ismultivalued>1</ismultivalued></column><column><name>TimeZone</name><data-type>Reference</data-type><isrequired>0</isrequired><ismultivalued>0</ismultivalued></column><column><name>Archive</name><data-type>String</data-type><isrequired>0</isrequired><ismultivalued>0</ismultivalued></column><column><name>Address1</name><data-type>String</data-type><isrequired>0</isrequired><ismultivalued>0</ismultivalued></column><column><name>AlumniType</name><data-type>String</data-type><isrequired>0</isrequired><ismultivalued>0</ismultivalued></column><column><name>Address3</name><data-type>String</data-type><isrequired>0</isrequired><ismultivalued>0</ismultivalued></column><column><name>Address2</name><data-type>String</data-type><isrequired>0</isrequired><ismultivalued>0</ismultivalued></column><column><name>ADSCODE1</name><data-type>String</data-type><isrequired>0</isrequired><ismultivalued>0</ismultivalued></column><column><name>AddressID</name><data-type>Integer</data-type><isrequired>0</isrequired><ismultivalued>0</ismultivalued></column><column><name>Deceased</name><data-type>String</data-type><isrequired>0</isrequired><ismultivalued>0</ismultivalued></column><column><name>DateLeft</name><data-type>DateTime</data-type><isrequired>0</isrequired><ismultivalued>0</ismultivalued></column><column><name>CandidateNumber</name><data-type>String</data-type><isrequired>0</isrequired><ismultivalued>0</ismultivalued></column><column><name>Class</name><data-type>String</data-type><isrequired>0</isrequired><ismultivalued>0</ismultivalued></column><column><name>PhoneHome</name><data-type>String</data-type><isrequired>0</isrequired><ismultivalued>0</ismultivalued></column><column><name>PersonType</name><data-type>String</data-type><isrequired>0</isrequired><ismultivalued>0</ismultivalued></column><column><name>PhoneMobile</name><data-type>String</data-type><isrequired>0</isrequired><ismultivalued>0</ismultivalued></column><column><name>NName</name><data-type>String</data-type><isrequired>0</isrequired><ismultivalued>0</ismultivalued></column><column><name>profilePath</name><data-type>String</data-type><isrequired>0</isrequired><ismultivalued>0</ismultivalued></column><column><name>PhoneFamily</name><data-type>String</data-type><isrequired>0</isrequired><ismultivalued>0</ismultivalued></column><column><name>PreEnrolment</name><data-type>String</data-type><isrequired>0</isrequired><ismultivalued>0</ismultivalued></column><column><name>ReasonLeft</name><data-type>String</data-type><isrequired>0</isrequired><ismultivalued>0</ismultivalued></column><column><name>Year</name><data-type>String</data-type><isrequired>0</isrequired><ismultivalued>0</ismultivalued></column><column><name>USIN</name><data-type>String</data-type><isrequired>0</isrequired><ismultivalued>0</ismultivalued></column><column><name>test</name><data-type>String</data-type><isrequired>0</isrequired><ismultivalued>0</ismultivalued></column><column><name>StudentType</name><data-type>String</data-type><isrequired>0</isrequired><ismultivalued>0</ismultivalued></column><column><name>StartYear</name><data-type>String</data-type><isrequired>0</isrequired><ismultivalued>0</ismultivalued></column><column><name>SAS2IDMConnector</name><data-type>Boolean</data-type><isrequired>0</isrequired><ismultivalued>0</ismultivalued></column><column><name>SchoolCode</name><data-type>String</data-type><isrequired>0</isrequired><ismultivalued>0</ismultivalued></column><column><name>Sex</name><data-type>String</data-type><isrequired>0</isrequired><ismultivalued>0</ismultivalued></column><column><name>StartDate</name><data-type>DateTime</data-type><isrequired>0</isrequired><ismultivalued>0</ismultivalued></column><column><name>SchoolID</name><data-type>Integer</data-type><isrequired>0</isrequired><ismultivalued>0</ismultivalued></column><column><name>EmployeeNumber</name><data-type>String</data-type><isrequired>0</isrequired><ismultivalued>0</ismultivalued></column><column><name>DOB</name><data-type>DateTime</data-type><isrequired>0</isrequired><ismultivalued>0</ismultivalued></column><column><name>Mailsuffix</name><data-type>String</data-type><isrequired>0</isrequired><ismultivalued>0</ismultivalued></column><column><name>FormerName</name><data-type>String</data-type><isrequired>0</isrequired><ismultivalued>0</ismultivalued></column><column><name>HomeGroup</name><data-type>String</data-type><isrequired>0</isrequired><ismultivalued>0</ismultivalued></column><column><name>House</name><data-type>String</data-type><isrequired>0</isrequired><ismultivalued>0</ismultivalued></column><column><name>PreferredName</name><data-type>String</data-type><isrequired>0</isrequired><ismultivalued>0</ismultivalued></column></column-info><column-info name="SynchronizationRule"><column><name>ObjectID</name><data-type>Reference</data-type><isrequired>0</isrequired><ismultivalued>0</ismultivalued></column><column><name>ConnectedObjectType</name><data-type>String</data-type><isrequired>1</isrequired><ismultivalued>0</ismultivalued></column><column><name>ConnectedSystem</name><data-type>String</data-type><isrequired>1</isrequired><ismultivalued>0</ismultivalued></column><column><name>ConnectedSystemScope</name><data-type>Text</data-type><isrequired>0</isrequired><ismultivalued>0</ismultivalued></column><column><name>CreateConnectedSystemObject</name><data-type>Boolean</data-type><isrequired>1</isrequired><ismultivalued>0</ismultivalued></column><column><name>CreatedTime</name><data-type>DateTime</data-type><isrequired>1</isrequired><ismultivalued>0</ismultivalued></column><column><name>CreateILMObject</name><data-type>Boolean</data-type><isrequired>1</isrequired><ismultivalued>0</ismultivalued></column><column><name>Creator</name><data-type>Reference</data-type><isrequired>0</isrequired><ismultivalued>0</ismultivalued></column><column><name>DeletedTime</name><data-type>DateTime</data-type><isrequired>0</isrequired><ismultivalued>0</ismultivalued></column><column><name>Dependency</name><data-type>Reference</data-type><isrequired>0</isrequired><ismultivalued>0</ismultivalued></column><column><name>Description</name><data-type>String</data-type><isrequired>0</isrequired><ismultivalued>0</ismultivalued></column><column><name>DetectedRulesList</name><data-type>Reference</data-type><isrequired>0</isrequired><ismultivalued>1</ismultivalued></column><column><name>DisconnectConnectedSystemObject</name><data-type>Boolean</data-type><isrequired>1</isrequired><ismultivalued>0</ismultivalued></column><column><name>DisplayName</name><data-type>String</data-type><isrequired>0</isrequired><ismultivalued>0</ismultivalued></column><column><name>ExistenceTest</name><data-type>Text</data-type><isrequired>0</isrequired><ismultivalued>1</ismultivalued></column><column><name>ExpectedRulesList</name><data-type>Reference</data-type><isrequired>0</isrequired><ismultivalued>1</ismultivalued></column><column><name>ExpirationTime</name><data-type>DateTime</data-type><isrequired>0</isrequired><ismultivalued>0</ismultivalued></column><column><name>FlowType</name><data-type>Integer</data-type><isrequired>1</isrequired><ismultivalued>0</ismultivalued></column><column><name>ILMObjectType</name><data-type>String</data-type><isrequired>1</isrequired><ismultivalued>0</ismultivalued></column><column><name>InitialFlow</name><data-type>Text</data-type><isrequired>0</isrequired><ismultivalued>1</ismultivalued></column><column><name>Locale</name><data-type>String</data-type><isrequired>0</isrequired><ismultivalued>0</ismultivalued></column><column><name>MVObjectID</name><data-type>String</data-type><isrequired>0</isrequired><ismultivalued>0</ismultivalued></column><column><name>ObjectType</name><data-type>String</data-type><isrequired>1</isrequired><ismultivalued>0</ismultivalued></column><column><name>PersistentFlow</name><data-type>Text</data-type><isrequired>0</isrequired><ismultivalued>1</ismultivalued></column><column><name>Precedence</name><data-type>Integer</data-type><isrequired>0</isrequired><ismultivalued>0</ismultivalued></column><column><name>RelationshipCriteria</name><data-type>String</data-type><isrequired>1</isrequired><ismultivalued>0</ismultivalued></column><column><name>ResourceTime</name><data-type>DateTime</data-type><isrequired>0</isrequired><ismultivalued>0</ismultivalued></column><column><name>SynchronizationRuleParameters</name><data-type>String</data-type><isrequired>0</isrequired><ismultivalued>1</ismultivalued></column><column><name>ManagementAgentID</name><data-type>Reference</data-type><isrequired>0</isrequired><ismultivalued>0</ismultivalued></column></column-info></mms-info><watermark>7f2b5f31-6c30-4ed4-b4a3-0774bc8b572a</watermark><connection-info><authentication>integrated</authentication><server>occcp-db004.dbb.local</server><databasename>FIMService</databasename><serviceHost>http://occcp-as034.dbb.local:5725</serviceHost><user>svcFIM_MA</user><domain>dbb</domain></connection-info></fimma-configuration>
 </private-configuration>
 <SyncConfig-refresh-schema>0</SyncConfig-refresh-schema>
 <ma-partition-data>
 <partition>
  <id>{9ABEFB01-8B4A-45F0-B652-EA735996ABDC}</id>
  <name>default</name>
  <creation-time>2011-12-23 04:49:23.283</creation-time>
  <last-modification-time>2012-03-05 03:07:45.883</last-modification-time>
  <version>6</version>
  <selected>1</selected>
  <filter>
   <object-classes>
    <object-class>DetectedRuleEntry</object-class>
    <object-class>ExpectedRuleEntry</object-class>
    <object-class>Group</object-class>
    <object-class>Person</object-class>
    <object-class>SynchronizationRule</object-class>
   </object-classes>
   <containers>
    <exclusions/>
    <inclusions>
     <inclusion></inclusion>
    </inclusions>
   </containers>
  </filter>
  <allowed-operations>31</allowed-operations>
  <current>
   <batch-number>201</batch-number>
   <sequence-number>1126404</sequence-number>
  </current>
  <last-successful-batch>200</last-successful-batch>
  <filter-hints>
   <object-classes>
    <object-class>
     <name>DetectedRuleEntry</name>
     <hierarchy>
      <object-class>DetectedRuleEntry</object-class>
     </hierarchy>
     <included>1</included>
    </object-class>
    <object-class>
     <name>ExpectedRuleEntry</name>
     <hierarchy>
      <object-class>ExpectedRuleEntry</object-class>
     </hierarchy>
     <included>1</included>
    </object-class>
    <object-class>
     <name>Group</name>
     <hierarchy>
      <object-class>Group</object-class>
     </hierarchy>
     <included>1</included>
    </object-class>
    <object-class>
     <name>Person</name>
     <hierarchy>
      <object-class>Person</object-class>
     </hierarchy>
     <included>1</included>
    </object-class>
    <object-class>
     <name>SynchronizationRule</name>
     <hierarchy>
      <object-class>SynchronizationRule</object-class>
     </hierarchy>
     <included>1</included>
    </object-class>
   </object-classes>
  </filter-hints>
 </partition>
</ma-partition-data>

 <ma-run-data>
 <run-configuration>
  <id>{06EDB454-3CBB-4BB7-8EC0-E58F32AA8BE4}</id>
  <name>Export to drop file</name>
  <creation-time>2012-02-29 00:19:20.127</creation-time>
  <version>1</version>
  <last-modification-time>2012-02-29 00:19:20.127</last-modification-time>
  <configuration><step><step-type type="export"><export-subtype>to-file</export-subtype></step-type><dropfile-name>FIM Export Drop File</dropfile-name><threshold></threshold><partition>{9ABEFB01-8B4A-45F0-B652-EA735996ABDC}</partition><custom-data><fimma-step-data><time-limit>90</time-limit></fimma-step-data></custom-data></step></configuration>
 </run-configuration>
 <run-configuration>
  <id>{9380636B-E539-4614-BC6F-DA285D3046E8}</id>
  <name>FI</name>
  <creation-time>2011-12-23 04:49:23.317</creation-time>
  <version>1</version>
  <last-modification-time>2011-12-23 04:49:23.317</last-modification-time>
  <configuration><step><step-type type="full-import"><import-subtype>to-cs</import-subtype></step-type><threshold></threshold><partition>{9ABEFB01-8B4A-45F0-B652-EA735996ABDC}</partition><custom-data></custom-data></step></configuration>
 </run-configuration>
 <run-configuration>
  <id>{4178DCEC-EF60-4B5B-9DB8-17650C20EBF5}</id>
  <name>FS</name>
  <creation-time>2011-12-23 04:49:23.330</creation-time>
  <version>1</version>
  <last-modification-time>2011-12-23 04:49:23.330</last-modification-time>
  <configuration><step><step-type type="apply-rules"><apply-rules-subtype>reevaluate-flow-connectors</apply-rules-subtype></step-type><threshold></threshold><partition>{9ABEFB01-8B4A-45F0-B652-EA735996ABDC}</partition><custom-data></custom-data></step></configuration>
 </run-configuration>
 <run-configuration>
  <id>{97604316-0385-4288-9536-AFA726F52285}</id>
  <name>Export</name>
  <creation-time>2011-12-23 04:49:23.330</creation-time>
  <version>1</version>
  <last-modification-time>2011-12-23 04:49:23.330</last-modification-time>
  <configuration><step><step-type type="export"></step-type><threshold></threshold><partition>{9ABEFB01-8B4A-45F0-B652-EA735996ABDC}</partition><custom-data><fimma-step-data><time-limit>90</time-limit></fimma-step-data></custom-data></step></configuration>
 </run-configuration>
 <run-configuration>
  <id>{81E3F52E-E351-4C0A-9A4C-EE3A804E9EAB}</id>
  <name>DI</name>
  <creation-time>2011-12-23 04:49:23.330</creation-time>
  <version>1</version>
  <last-modification-time>2011-12-23 04:49:23.330</last-modification-time>
  <configuration><step><step-type type="delta-import"><import-subtype>to-cs</import-subtype></step-type><threshold></threshold><partition>{9ABEFB01-8B4A-45F0-B652-EA735996ABDC}</partition><custom-data></custom-data></step></configuration>
 </run-configuration>
 <run-configuration>
  <id>{07109888-13C7-4918-A3E1-599B8EE822D0}</id>
  <name>DS</name>
  <creation-time>2011-12-23 04:49:23.330</creation-time>
  <version>1</version>
  <last-modification-time>2011-12-23 04:49:23.330</last-modification-time>
  <configuration><step><step-type type="apply-rules"><apply-rules-subtype>apply-pending</apply-rules-subtype></step-type><threshold></threshold><partition>{9ABEFB01-8B4A-45F0-B652-EA735996ABDC}</partition><custom-data></custom-data></step></configuration>
 </run-configuration>
 <run-configuration>
  <id>{1B071DC6-4438-433B-A886-F468C9DF1C5E}</id>
  <name>DI and DS</name>
  <creation-time>2011-12-23 04:49:23.330</creation-time>
  <version>1</version>
  <last-modification-time>2011-12-23 04:49:23.330</last-modification-time>
  <configuration><step><step-type type="delta-import"></step-type><threshold></threshold><partition>{9ABEFB01-8B4A-45F0-B652-EA735996ABDC}</partition><custom-data></custom-data></step></configuration>
 </run-configuration>
 <run-configuration>
  <id>{3E4EA4F6-719D-42B4-B34F-3C75762AFD1A}</id>
  <name>Export DI DS</name>
  <creation-time>2011-12-23 04:49:23.330</creation-time>
  <version>1</version>
  <last-modification-time>2011-12-23 04:49:23.330</last-modification-time>
  <configuration><step><step-type type="export"></step-type><threshold></threshold><partition>{9ABEFB01-8B4A-45F0-B652-EA735996ABDC}</partition><custom-data><fimma-step-data><time-limit>90</time-limit></fimma-step-data></custom-data></step><step><step-type type="delta-import"><import-subtype>to-cs</import-subtype></step-type><threshold></threshold><partition>{9ABEFB01-8B4A-45F0-B652-EA735996ABDC}</partition><custom-data></custom-data></step><step><step-type type="apply-rules"><apply-rules-subtype>apply-pending</apply-rules-subtype></step-type><threshold></threshold><partition>{9ABEFB01-8B4A-45F0-B652-EA735996ABDC}</partition><custom-data></custom-data></step></configuration>
 </run-configuration>
 <run-configuration>
  <id>{AF59C59F-C782-4224-9AB8-7B099B214F12}</id>
  <name>FI FS</name>
  <creation-time>2011-12-23 04:49:23.330</creation-time>
  <version>1</version>
  <last-modification-time>2011-12-23 04:49:23.330</last-modification-time>
  <configuration><step><step-type type="full-import"><import-subtype>to-cs</import-subtype></step-type><threshold></threshold><partition>{9ABEFB01-8B4A-45F0-B652-EA735996ABDC}</partition><custom-data></custom-data></step><step><step-type type="apply-rules"><apply-rules-subtype>reevaluate-flow-connectors</apply-rules-subtype></step-type><threshold></threshold><partition>{9ABEFB01-8B4A-45F0-B652-EA735996ABDC}</partition><custom-data></custom-data></step></configuration>
 </run-configuration>
 <run-configuration>
  <id>{DF9DD4F8-E3E8-4A16-AA9B-D985CE294483}</id>
  <name>DI DS - One Step</name>
  <creation-time>2011-12-23 04:49:23.330</creation-time>
  <version>1</version>
  <last-modification-time>2011-12-23 04:49:23.330</last-modification-time>
  <configuration><step><step-type type="delta-import"></step-type><threshold></threshold><partition>{9ABEFB01-8B4A-45F0-B652-EA735996ABDC}</partition><custom-data></custom-data></step></configuration>
 </run-configuration>
</ma-run-data>

 <capabilities-mask>40b805</capabilities-mask>
 <export-type>1</export-type>
 <dn-construction><attribute>ObjectID</attribute></dn-construction>
 <password-sync><maximum-retry-count>10</maximum-retry-count><retry-interval>60</retry-interval><allow-low-security>0</allow-low-security></password-sync>
 <component_mappings />
</ma-data>

</saved-ma-configuration>
